SidewinderFFB2.cp311-win_amd64.pyd
sidewinderffb2-0.0.1.dist-info/METADATA
sidewinderffb2-0.0.1.dist-info/WHEEL
sidewinderffb2-0.0.1.dist-info/RECORD
