Metadata-Version: 2.1
Name: SidewinderFFB2
Version: 0.0.1
Summary: Bindings for a Microsoft Sidewinder Force Feedback 2 joystick.
Author-Email: Keith Baston <keith.baston@gmail.com>
Classifier: Programming Language :: Python :: 3
Classifier: License :: OSI Approved :: MIT License
Classifier: Operating System :: Microsoft :: Windows
Project-URL: Repository, https://github.com/HappyFox/SidewinderFFB2
Requires-Python: >=3.8
